aplicacion_de_ventas/__init__.py
aplicacion_ventas_cgian-0.1.0.dist-info/licenses/LICENCE
tests/Test_Aplicacion_Ventas.py
tests/Usar_Aplicacion_Ventas.py
tests/__init__.py
aplicacion_ventas_cgian-0.1.0.dist-info/METADATA
aplicacion_ventas_cgian-0.1.0.dist-info/WHEEL
aplicacion_ventas_cgian-0.1.0.dist-info/top_level.txt
aplicacion_ventas_cgian-0.1.0.dist-info/RECORD
