Metadata-Version: 2.4
Name: aplicacion_ventas_cgian
Version: 0.1.0
Summary: Paquetes para gestionar ventas, precios, impuestos, y descuentos
Home-page: https://github.com/curso_python_camara/gestor/aplicacionventas
Author: Cesar
Author-email: cesargianfranko@gmai.com
Classifier: Programming Language :: Python :: 3
Classifier: License :: OSI Approved :: MIT License
Classifier: Operating System :: OS Independent
Requires-Python: >=3.7
License-File: LICENCE
Dynamic: author
Dynamic: author-email
Dynamic: classifier
Dynamic: description
Dynamic: description-content-type
Dynamic: home-page
Dynamic: license-file
Dynamic: requires-python
Dynamic: summary
